py_cert_store-0.3.0.dist-info/METADATA
py_cert_store-0.3.0.dist-info/WHEEL
py_cert_store-0.3.0.dist-info/licenses/LICENSE
py_cert_store/__about__.py
py_cert_store/__init__.py
py_cert_store/py_cert_store.cp313-win_amd64.pyd
py_cert_store/py_cert_store.pyi
py_cert_store-0.3.0.dist-info/RECORD
