Metadata-Version: 2.4
Name: py_cert_store
Version: 0.3.0
Classifier: Development Status :: 5 - Production/Stable
Classifier: Programming Language :: Rust
Classifier: Programming Language :: Python :: Implementation :: CPython
Classifier: Programming Language :: Python :: Implementation :: PyPy
Requires-Dist: cryptography>=44.0.1
Requires-Dist: pythonnet ; extra == 'tests'
Provides-Extra: tests
License-File: LICENSE
License-Expression: Apache-2.0 license
Requires-Python: >=3.8
Project-URL: Homepage, https://github.com/unwarymold9171/Py_Cert_Store
Project-URL: Issues, https://github.com/unwarymold9171/Py_Cert_Store/issues
